project_file_tree/__init__.py
project_file_tree/prft.py
prft-1.3.0.dist-info/LICENSE.txt
prft-1.3.0.dist-info/METADATA
prft-1.3.0.dist-info/WHEEL
prft-1.3.0.dist-info/entry_points.txt
prft-1.3.0.dist-info/top_level.txt
prft-1.3.0.dist-info/RECORD
