Metadata-Version: 2.1
Name: prft
Version: 1.3.0
Summary: A tool to generate a file tree structure of a project with .gitignore support
Author-email: Arkadii Artamonov <artamarkan@gmail.com>
Maintainer-email: Arkadii Artamonov <artamarkan@gmail.com>
License: MIT License
Keywords: file,tree,structure,file tree,file structure
Classifier: Development Status :: 4 - Beta
Classifier: Programming Language :: Python :: 3
Classifier: License :: OSI Approved :: MIT License
Classifier: Operating System :: OS Independent
Requires-Python: >=3.8
License-File: LICENSE.txt
Requires-Dist: pathspec
